subcommandir/__init__.py
subcommandir/tests/__init__.py
subcommandir/tests/test_subcommandir.py
subcommandir/tests/tests_subcommandir_app/__init__.py
subcommandir/tests/tests_subcommandir_app/management/__init__.py
subcommandir/tests/tests_subcommandir_app/management/commands/__init__.py
subcommandir/tests/tests_subcommandir_app/management/commands/tests_subcommandir_load.py
subcommandir/tests/tests_subcommandir_app/management/commands/load/__init__.py
subcommandir/tests/tests_subcommandir_app/management/commands/load/month_report.py
subcommandir/tests/tests_subcommandir_app/management/commands/load/year_report.py
django_subcommandir-0.3.0.dist-info/LICENSE
django_subcommandir-0.3.0.dist-info/METADATA
django_subcommandir-0.3.0.dist-info/WHEEL
django_subcommandir-0.3.0.dist-info/top_level.txt
django_subcommandir-0.3.0.dist-info/RECORD
