Metadata-Version: 2.1
Name: django-subcommandir
Version: 0.3.0
Summary: Django subcommands in subdirectories
Home-page: https://github.com/pikhovkin/django-subcommandir
Author: Sergei Pikhovkin
Author-email: s@pikhovkin.ru
License: MIT
Keywords: django,command,commands,django-commands,django-subcommands
Classifier: Development Status :: 3 - Alpha
Classifier: Environment :: Web Environment
Classifier: Framework :: Django :: 3.0
Classifier: Framework :: Django :: 3.1
Classifier: Framework :: Django :: 3.2
Classifier: Framework :: Django :: 4.0
Classifier: Framework :: Django :: 4.1
Classifier: Framework :: Django :: 4.2
Classifier: Intended Audience :: Developers
Classifier: License :: OSI Approved :: MIT License
Classifier: Operating System :: OS Independent
Classifier: Programming Language :: Python :: 3 :: Only
Classifier: Programming Language :: Python :: 3.7
Classifier: Programming Language :: Python :: 3.8
Classifier: Programming Language :: Python :: 3.9
Classifier: Programming Language :: Python :: 3.10
Classifier: Programming Language :: Python :: 3.11
Requires-Python: >=3.7,<4.0
License-File: LICENSE
Requires-Dist: Django (<4.2,>=3.1)
